rest_framework_jwt/__init__.py
rest_framework_jwt/authentication.py
rest_framework_jwt/compat.py
rest_framework_jwt/models.py
rest_framework_jwt/serializers.py
rest_framework_jwt/settings.py
rest_framework_jwt/test.py
rest_framework_jwt/utils.py
rest_framework_jwt/views.py
rest_framework_jwt/locale/en_US/LC_MESSAGES/django.po
djangorestframework_jwt_joinup-1.12.2.dist-info/LICENSE
djangorestframework_jwt_joinup-1.12.2.dist-info/METADATA
djangorestframework_jwt_joinup-1.12.2.dist-info/WHEEL
djangorestframework_jwt_joinup-1.12.2.dist-info/top_level.txt
djangorestframework_jwt_joinup-1.12.2.dist-info/RECORD
